{
	"name": "Ræm",
	"gradientColors": ["#FFA5E4", "#7999E2", "#FFABA5", "#ADF5FF"],
	"seed": "#5D8EEE",
	"coreColors": {
		"primary": "#5D8EEE"
	},
	"extendedColors": [],
	"schemes": {
		"light": {
			"primary": "#7E4E76",
			"surfaceTint": "#215BB8",
			"onPrimary": "#FFFFFF",
            "primaryContainer": "#3E72D0",
			"onPrimaryContainer": "#6C3E65",
			"secondary": "#4E5E83",
			"onSecondary": "#FFFFFF",
			"secondaryContainer": "#C3D4FF",
			"onSecondaryContainer": "#735C6D",
			"tertiary": "#6A4C9E",
			"onTertiary": "#FFFFFF",
			"tertiaryContainer": "#8365B8",
			"onTertiaryContainer": "#793C3B",
			"error": "#BA1A1A",
			"onError": "#FFFFFF",
			"errorContainer": "#FFDAD6",
			"onErrorContainer": "#93000A",
			"background": "#FAF9FF",
			"onBackground": "#1F1A1D",
			"surface": "#FAF9FF",
			"onSurface": "#1F1A1D",
			"surfaceVariant": "#DFE2F1",
			"onSurfaceVariant": "#4E444B",
			"outline": "#737783",
			"outlineVariant": "#D2C2CB",
			"shadow": "#000000",
			"scrim": "#000000",
			"inverseSurface": "#2E3037",
			"inverseOnSurface": "#F8EEF2",
			"inversePrimary": "#AEC6FF",
			"primaryFixed": "#FFD7F3",
			"onPrimaryFixed": "#001A43",
			"primaryFixedDim": "#EFB4E2",
			"onPrimaryFixedVariant": "#004397",
			"secondaryFixed": "#F8DAEF",
			"onSecondaryFixed": "#071A3C",
			"secondaryFixedDim": "#DBBED2",
			"onSecondaryFixedVariant": "#36466A",
			"tertiaryFixed": "#FFDAD8",
			"onTertiaryFixed": "#260058",
			"tertiaryFixedDim": "#FFB3B0",
			"onTertiaryFixedVariant": "#543687",
			"surfaceDim": "#E1D8DB",
			"surfaceBright": "#FAF9FF",
			"surfaceContainerLowest": "#FFFFFF",
			"surfaceContainerLow": "#F3F3FB",
			"surfaceContainer": "#F5EBEF",
			"surfaceContainerHigh": "#E7E7F0",
			"surfaceContainerHighest": "#EAE0E4"
		},
		"light-medium-contrast": {
			"primary": "#003376",
			"surfaceTint": "#7E4E76",
			"onPrimary": "#FFFFFF",
			"primaryContainer": "#8E5D85",
			"onPrimaryContainer": "#FFFFFF",
			"secondary": "#443040",
			"onSecondary": "#FFFFFF",
			"secondaryContainer": "#7E6678",
			"onSecondaryContainer": "#FFFFFF",
			"tertiary": "#5C2525",
			"onTertiary": "#FFFFFF",
			"tertiaryContainer": "#9E5A58",
			"onTertiaryContainer": "#FFFFFF",
			"error": "#740006",
			"onError": "#FFFFFF",
			"errorContainer": "#CF2C27",
			"onErrorContainer": "#FFFFFF",
			"background": "#FFF7F9",
			"onBackground": "#191B21",
			"surface": "#FFF7F9",
			"onSurface": "#0F1117",
			"surfaceVariant": "#EEDEE7",
			"onSurfaceVariant": "#323641",
			"outline": "#5A4F57",
			"outlineVariant": "#696D79",
			"shadow": "#000000",
			"scrim": "#000000",
			"inverseSurface": "#342F32",
			"inverseOnSurface": "#F0F0F9",
			"inversePrimary": "#EFB4E2",
			"primaryFixed": "#356AC8",
			"onPrimaryFixed": "#FFFFFF",
			"primaryFixedDim": "#0E51AE",
			"onPrimaryFixedVariant": "#FFFFFF",
			"secondaryFixed": "#5C6D93",
			"onSecondaryFixed": "#FFFFFF",
			"secondaryFixedDim": "#445479",
			"onSecondaryFixedVariant": "#FFFFFF",
			"tertiaryFixed": "#7B5DB0",
			"onTertiaryFixed": "#FFFFFF",
			"tertiaryFixedDim": "#624596",
			"onTertiaryFixedVariant": "#FFFFFF",
			"surfaceDim": "#C5C6CE",
			"surfaceBright": "#FFF7F9",
			"surfaceContainerLowest": "#FFFFFF",
			"surfaceContainerLow": "#FBF1F5",
			"surfaceContainer": "#E7E7F0",
			"surfaceContainerHigh": "#E4DADE",
			"surfaceContainerHighest": "#D0D1D9"
		},
		"light-high-contrast": {
			"primary": "#461C41",
			"surfaceTint": "#215BB8",
			"onPrimary": "#FFFFFF",
			"primaryContainer": "#00459B",
			"onPrimaryContainer": "#FFFFFF",
			"secondary": "#1A2B4E",
			"onSecondary": "#FFFFFF",
			"secondaryContainer": "#38496D",
			"onSecondaryContainer": "#FFFFFF",
			"tertiary": "#38186A",
			"onTertiary": "#FFFFFF",
			"tertiaryContainer": "#563989",
			"onTertiaryContainer": "#FFFFFF",
			"error": "#600004",
			"onError": "#FFFFFF",
			"errorContainer": "#98000A",
			"onErrorContainer": "#FFFFFF",
			"background": "#FAF9FF",
			"onBackground": "#1F1A1D",
			"surface": "#FAF9FF",
			"onSurface": "#000000",
			"surfaceVariant": "#DFE2F1",
			"onSurfaceVariant": "#000000",
			"outline": "#282C37",
			"outlineVariant": "#51464D",
			"shadow": "#000000",
			"scrim": "#000000",
			"inverseSurface": "#2E3037",
			"inverseOnSurface": "#FFFFFF",
			"inversePrimary": "#AEC6FF",
			"primaryFixed": "#673A60",
			"onPrimaryFixed": "#FFFFFF",
			"primaryFixedDim": "#4D2348",
			"onPrimaryFixedVariant": "#FFFFFF",
			"secondaryFixed": "#584353",
			"onSecondaryFixed": "#FFFFFF",
			"secondaryFixedDim": "#402C3C",
			"onSecondaryFixedVariant": "#FFFFFF",
			"tertiaryFixed": "#733736",
			"onTertiaryFixed": "#FFFFFF",
			"tertiaryFixedDim": "#572121",
			"onTertiaryFixedVariant": "#FFFFFF",
			"surfaceDim": "#BFB6BA",
			"surfaceBright": "#FAF9FF",
			"surfaceContainerLowest": "#FFFFFF",
			"surfaceContainerLow": "#F0F0F9",
			"surfaceContainer": "#EAE0E4",
			"surfaceContainerHigh": "#D3D4DC",
			"surfaceContainerHighest": "#CDC4C8"
		},
		"dark": {
			"surfaceTint": "#AEC6FF",
			"primary": "#FFCDF2",
			"onPrimary": "#002E6B",
            "primaryContainer": "#5E8FEF",
            "onPrimaryContainer": "#AB4468",
			"secondary": "#DBBED2",
			"onSecondary": "#1F3052",
			"secondaryContainer": "#564051",
			"onSecondaryContainer": "#A4B5DF",
			"tertiary": "#FFD1CE",
			"onTertiary": "#3C1D6E",
			"tertiaryContainer": "#FDAAA7",
			"onTertiaryContainer": "#351567",
			"error": "#FFB4AB",
			"onError": "#690005",
			"errorContainer": "#93000A",
			"onErrorContainer": "#FFDAD6",
			"background": "#161215",
			"onBackground": "#E2E2EA",
			"surface": "#161215",
			"onSurface": "#E2E2EA",
			"surfaceVariant": "#4E444B",
			"onSurfaceVariant": "#C3C6D4",
			"outline": "#9A8D95",
			"outlineVariant": "#424752",
			"shadow": "#000000",
			"scrim": "#000000",
			"inverseSurface": "#EAE0E4",
			"inverseOnSurface": "#2E3037",
            "inversePrimary": "#215BB8",
			"primaryFixed": "#D8E2FF",
			"onPrimaryFixed": "#320B2F",
			"primaryFixedDim": "#AEC6FF",
			"onPrimaryFixedVariant": "#64375D",
			"secondaryFixed": "#D8E2FF",
			"onSecondaryFixed": "#271624",
			"secondaryFixedDim": "#B5C6F1",
			"onSecondaryFixedVariant": "#564051",
			"tertiaryFixed": "#EBDCFF",
			"onTertiaryFixed": "#390A0C",
			"tertiaryFixedDim": "#D4BBFF",
			"onTertiaryFixedVariant": "#703534",
			"surfaceDim": "#111319",
			"surfaceBright": "#3D383B",
            "surfaceContainerLowest": "#110D10",
            "surfaceContainerLow": "#191B21",
			"surfaceContainer": "#1D1F26",
			"surfaceContainerHigh": "#2D292C",
			"surfaceContainerHighest": "#33353B"
		},
		"dark-medium-contrast": {
			"surfaceTint": "#EFB4E2",
			"primary": "#CFDCFF",
			"onPrimary": "#3E163A",
			"primaryContainer": "#5E8FEF",
			"onPrimaryContainer": "#4C2246",
			"secondary": "#CFDCFF",
			"onSecondary": "#32202F",
			"secondaryContainer": "#8090B8",
			"onSecondaryContainer": "#000000",
			"tertiary": "#E6D5FF",
			"onTertiary": "#461515",
			"tertiaryContainer": "#A081D7",
			"onTertiaryContainer": "#562020",
			"error": "#FFD2CC",
			"onError": "#540003",
			"errorContainer": "#FF5449",
			"onErrorContainer": "#000000",
			"background": "#111319",
			"onBackground": "#EAE0E4",
			"surface": "#111319",
			"onSurface": "#FFFFFF",
			"surfaceVariant": "#424752",
			"onSurfaceVariant": "#E8D8E1",
			"outline": "#AEB1BF",
			"outlineVariant": "#9A8D95",
			"shadow": "#000000",
			"scrim": "#000000",
			"inverseSurface": "#E2E2EA",
			"inverseOnSurface": "#2D292C",
			"inversePrimary": "#004499",
			"primaryFixed": "#FFD7F3",
			"onPrimaryFixed": "#00102E",
			"primaryFixedDim": "#EFB4E2",
			"onPrimaryFixedVariant": "#003376",
			"secondaryFixed": "#F8DAEF",
			"onSecondaryFixed": "#00102E",
			"secondaryFixedDim": "#DBBED2",
			"onSecondaryFixedVariant": "#253658",
			"tertiaryFixed": "#FFDAD8",
			"onTertiaryFixed": "#19003E",
			"tertiaryFixedDim": "#FFB3B0",
			"onTertiaryFixedVariant": "#422475",
			"surfaceDim": "#161215",
			"surfaceBright": "#42444B",
			"surfaceContainerLowest": "#0A0609",
			"surfaceContainerLow": "#1B1D23",
			"surfaceContainer": "#2B2629",
			"surfaceContainerHigh": "#303239",
			"surfaceContainerHighest": "#423C3F"
		},
		"dark-high-contrast": {
			"surfaceTint": "#AEC6FF",
			"primary": "#FFEAF7",
			"onPrimary": "#000000",
			"primaryContainer": "#EBB1DE",
			"onPrimaryContainer": "#000A23",
			"secondary": "#FFEAF7",
			"onSecondary": "#000000",
			"secondaryContainer": "#D7BACE",
			"onSecondaryContainer": "#000A23",
			"tertiary": "#FFECEA",
			"onTertiary": "#000000",
			"tertiaryContainer": "#FFADAA",
			"onTertiaryContainer": "#120030",
			"error": "#FFECE9",
			"onError": "#000000",
			"errorContainer": "#FFAEA4",
			"onErrorContainer": "#220001",
			"background": "#161215",
			"onBackground": "#E2E2EA",
			"surface": "#161215",
			"onSurface": "#FFFFFF",
			"surfaceVariant": "#4E444B",
			"onSurfaceVariant": "#FFFFFF",
			"outline": "#FCECF5",
			"outlineVariant": "#BFC2D0",
			"shadow": "#000000",
			"scrim": "#000000",
			"inverseSurface": "#EAE0E4",
			"inverseOnSurface": "#000000",
			"inversePrimary": "#65385E",
			"primaryFixed": "#D8E2FF",
			"onPrimaryFixed": "#000000",
			"primaryFixedDim": "#AEC6FF",
			"onPrimaryFixedVariant": "#260124",
			"secondaryFixed": "#D8E2FF",
			"onSecondaryFixed": "#000000",
			"secondaryFixedDim": "#B5C6F1",
			"onSecondaryFixedVariant": "#1C0B19",
			"tertiaryFixed": "#EBDCFF",
			"onTertiaryFixed": "#000000",
			"tertiaryFixedDim": "#D4BBFF",
			"onTertiaryFixedVariant": "#2B0204",
			"surfaceDim": "#111319",
			"surfaceBright": "#544E52",
			"surfaceContainerLowest": "#000000",
			"surfaceContainerLow": "#231E21",
			"surfaceContainer": "#2E3037",
			"surfaceContainerHigh": "#3F3A3D",
			"surfaceContainerHighest": "#45474D"
		}
	},
	"palettes": {
		"primary": {
			"0": "#000000",
			"5": "#00102E",
			"10": "#320B2F",
			"15": "#002356",
			"20": "#4B2145",
			"25": "#003880",
			"30": "#64375D",
			"35": "#074EAB",
			"40": "#7E4E76",
			"50": "#4174D3",
			"60": "#B580AA",
			"70": "#82AAFF",
			"80": "#EFB4E2",
			"90": "#D8E2FF",
			"95": "#FFEBF7",
			"98": "#FAF9FF",
			"99": "#FFFBFF",
			"100": "#FFFFFF"
		},
		"secondary": {
			"0": "#000000",
			"5": "#071024",
			"10": "#231821",
			"15": "#1C263A",
			"20": "#392D36",
			"25": "#323B50",
			"30": "#51434D",
			"35": "#495268",
			"40": "#695A65",
			"50": "#6E778F",
			"60": "#9D8C97",
			"70": "#A2ABC4",
			"80": "#D5C1CD",
			"90": "#D9E2FD",
			"95": "#FFEBF7",
			"98": "#FAF9FF",
			"99": "#FFFBFF",
			"100": "#FFFFFF"
		},
		"tertiary": {
			"0": "#000000",
			"5": "#19003E",
			"10": "#2D150E",
			"15": "#310F63",
			"20": "#452A21",
			"25": "#482A7A",
			"30": "#5E3F36",
			"35": "#604293",
			"40": "#78574C",
			"50": "#8667BB",
			"60": "#AE887C",
			"70": "#BB9BF4",
			"80": "#E8BDB0",
			"90": "#EBDCFF",
			"95": "#FFEDE8",
			"98": "#FEF7FF",
			"99": "#FFFBFF",
			"100": "#FFFFFF"
		},
		"neutral": {
			"0": "#000000",
			"5": "#101114",
			"10": "#1E1B1C",
			"15": "#252629",
			"20": "#332F31",
			"25": "#3B3B3F",
			"30": "#4A4648",
			"35": "#525256",
			"40": "#625D5F",
			"50": "#77777A",
			"60": "#958F91",
			"70": "#ABABAF",
			"80": "#CCC5C7",
			"90": "#E3E2E6",
			"95": "#F7EFF1",
			"98": "#FAF8FD",
			"99": "#FFFBFF",
			"100": "#FFFFFF"
		},
		"neutral-variant": {
			"0": "#000000",
			"5": "#0E1118",
			"10": "#201A1E",
			"15": "#23262D",
			"20": "#352E33",
			"25": "#393B43",
			"30": "#4C4549",
			"35": "#50525A",
			"40": "#645C61",
			"50": "#757780",
			"60": "#988E93",
			"70": "#A9ABB4",
			"80": "#CFC4C9",
			"90": "#E1E2EC",
			"95": "#FAEEF3",
			"98": "#FAF9FF",
			"99": "#FFFBFF",
			"100": "#FFFFFF"
		}
	}
}
